setup.cfg
setup.py
py_readability.egg-info/PKG-INFO
py_readability.egg-info/SOURCES.txt
py_readability.egg-info/dependency_links.txt
py_readability.egg-info/requires.txt
py_readability.egg-info/top_level.txt
pyreadability/__init__.py
pyreadability/readability.py