Metadata-Version: 1.1
Name: py-readability
Version: 1.0
Summary: Calculate readability index values
Home-page: https://github.com/mattselph/readability
Author: Matt Selph
Author-email: matt@mattselph.io
License: UNKNOWN
Download-URL: https://github.com/mattselph/readability/tarball/1.0
Keywords: readability
Platform: UNKNOWN
